Metadata-Version: 2.1
Name: galsampler
Version: 0.1.1
Summary: Galsampler algorithms used for generating synthetic cosmological data
Author-email: Andrew Hearin <ahearin@anl.gov>
License: BSD 3-Clause License
Project-URL: home, https://github.com/LSSTDESC/galsampler
Classifier: Programming Language :: Python :: 3
Requires-Python: >=3.8
License-File: LICENSE.rst
Requires-Dist: numpy
Requires-Dist: scipy
Requires-Dist: numba
